datapipelab/__init__.py
datapipelab/engine.py
datapipelab/logger.py
datapipelab/pipeline.py
datapipelab/pipeline_config.py
datapipelab/pipeline_handler.py
datapipelab/app/__init__.py
datapipelab/app/connector_node/__init__.py
datapipelab/app/node/__init__.py
datapipelab/app/node/custom_node.py
datapipelab/app/node/tnode.py
datapipelab/app/node/processor/__init__.py
datapipelab/app/node/processor/bigquery_api_node.py
datapipelab/app/node/processor/bigquery_spark_node.py
datapipelab/app/node/processor/custom_node.py
datapipelab/app/node/processor/gcp_bucket_node.py
datapipelab/app/node/processor/shell_node.py
datapipelab/app/node/processor/spark_node.py
datapipelab/app/node/sink/__init__.py
datapipelab/app/node/sink/csv_node.py
datapipelab/app/node/sink/delta_node.py
datapipelab/app/node/sink/hive_node.py
datapipelab/app/node/sink/pandas_csv_node.py
datapipelab/app/node/sink/spark_api_node.py
datapipelab/app/node/sink/spark_node.py
datapipelab/app/node/sink/teams_notification_node.py
datapipelab/app/node/source/__init__.py
datapipelab/app/node/source/delta_node.py
datapipelab/app/node/source/hive_node.py
datapipelab/app/node/source/spark_api_node.py
datapipelab/app/node/source/spark_node.py
datapipelab/app/wrapper/__init__.py
datapipelab/app/wrapper/source/__init__.py
datapipelab-0.3.7.dist-info/METADATA
datapipelab-0.3.7.dist-info/WHEEL
datapipelab-0.3.7.dist-info/top_level.txt
datapipelab-0.3.7.dist-info/RECORD
