Metadata-Version: 2.4
Name: datapipelab
Version: 0.3.7
Summary: A data pipeline library with connectors, sources, processors, and sinks.
Requires-Dist: json5
Requires-Dist: loguru
Dynamic: description
Dynamic: description-content-type
Dynamic: requires-dist
Dynamic: summary
